{
  "id": "7e52555d-e48b-46f2-84e5-118336f2398b",
  "prevId": "9fbb69d2-2786-475c-b212-491d5b577ba0",
  "version": "7",
  "dialect": "postgresql",
  "tables": {
    "public.clients": {
      "name": "clients",
      "schema": "",
      "columns": {
        "id": {
          "name": "id",
          "type": "serial",
          "primaryKey": true,
          "notNull": true
        },
        "name": {
          "name": "name",
          "type": "varchar",
          "primaryKey": false,
          "notNull": true
        },
        "slug": {
          "name": "slug",
          "type": "varchar",
          "primaryKey": false,
          "notNull": true
        },
        "endpoint": {
          "name": "endpoint",
          "type": "varchar",
          "primaryKey": false,
          "notNull": true
        },
        "last_polled_at": {
          "name": "last_polled_at",
          "type": "timestamp",
          "primaryKey": false,
          "notNull": false
        },
        "updated_at": {
          "name": "updated_at",
          "type": "timestamp",
          "primaryKey": false,
          "notNull": true,
          "default": "now()"
        },
        "created_at": {
          "name": "created_at",
          "type": "timestamp",
          "primaryKey": false,
          "notNull": true,
          "default": "now()"
        }
      },
      "indexes": {},
      "foreignKeys": {},
      "compositePrimaryKeys": {},
      "uniqueConstraints": {},
      "policies": {},
      "checkConstraints": {},
      "isRLSEnabled": false
    }
  },
  "enums": {},
  "schemas": {},
  "sequences": {},
  "roles": {},
  "policies": {},
  "views": {},
  "_meta": {
    "columns": {},
    "schemas": {},
    "tables": {}
  }
}